{
	"configurations" : 
	[
		{
			"directories" : 
			[
				{
					"build" : ".",
					"jsonFile" : "directory-.-Debug-d0094a50bb2071803777.json",
					"minimumCMakeVersion" : 
					{
						"string" : "3.28"
					},
					"projectIndex" : 0,
					"source" : ".",
					"targetIndexes" : 
					[
						0
					]
				}
			],
			"name" : "Debug",
			"projects" : 
			[
				{
					"directoryIndexes" : 
					[
						0
					],
					"name" : "sheet10",
					"targetIndexes" : 
					[
						0
					]
				}
			],
			"targets" : 
			[
				{
					"directoryIndex" : 0,
					"id" : "sheet10::@6890427a1f51a3e7e1df",
					"jsonFile" : "target-sheet10-Debug-0a821f303f7c76e501ec.json",
					"name" : "sheet10",
					"projectIndex" : 0
				}
			]
		}
	],
	"kind" : "codemodel",
	"paths" : 
	{
		"build" : "D:/Projects/perf-oriented-dev/exercises/sheet10/cmake-build-debug",
		"source" : "D:/Projects/perf-oriented-dev/exercises/sheet10"
	},
	"version" : 
	{
		"major" : 2,
		"minor" : 6
	}
}
